{
  "count": 24,
  "value": [
    {
      "id": 3,
      "rev": 8,
      "fields": {
        "System.AreaPath": "$ProjectName$",
        "System.TeamProject": "$ProjectName$",
        "System.IterationPath": "$ProjectName$",
        "System.WorkItemType": "User Story",
        "System.State": "New",
        "System.Reason": "New",
        "System.CreatedDate": "2019-04-03T19:27:31.86Z",
        "System.CreatedBy": "Brian Blanchard <brblanch@microsoft.com>",
        "System.ChangedDate": "2019-06-28T16:56:27.07Z",
        "System.ChangedBy": "Brian Blanchard <brblanch@microsoft.com>",
        "System.Title": "Prerequisites",
        "Microsoft.VSTS.Scheduling.Effort": 0.0,
        "System.Description": "Validate completion of prerequisites &amp; document answers",
        "System.AssignedTo": null,
        "Microsoft.VSTS.Scheduling.RemainingWork": 0.0,
        "Microsoft.VSTS.Common.Priority": 2.0,
        "System.BoardLane": null,
        "System.Tags": "Workload Template",
        "Microsoft.VSTS.TCM.Steps": null,
        "Microsoft.VSTS.TCM.Parameters": null,
        "Microsoft.VSTS.TCM.LocalDataSource": null,
        "Microsoft.VSTS.TCM.AutomationStatus": null,
        "System.History": null
      },
      "relations": [
        {
          "rel": "System.LinkTypes.Hierarchy-Reverse",
          "url": "https://dev.azure.com/CAFTemplate/_apis/wit/workItems/83",
          "attributes": {
            "isLocked": "false",
            "name": "Parent"
          }
        },
        {
          "rel": "System.LinkTypes.Hierarchy-Forward",
          "url": "https://dev.azure.com/CAFTemplate/_apis/wit/workItems/5",
          "attributes": {
            "isLocked": "false",
            "name": "Child"
          }
        },
        {
          "rel": "System.LinkTypes.Hierarchy-Forward",
          "url": "https://dev.azure.com/CAFTemplate/_apis/wit/workItems/6",
          "attributes": {
            "isLocked": "false",
            "name": "Child"
          }
        },
        {
          "rel": "System.LinkTypes.Hierarchy-Forward",
          "url": "https://dev.azure.com/CAFTemplate/_apis/wit/workItems/4",
          "attributes": {
            "isLocked": "false",
            "name": "Child"
          }
        }
      ],
      "url": "https://dev.azure.com/CAFTemplate/_apis/wit/workItems/3"
    },
    {
      "id": 134,
      "rev": 6,
      "fields": {
        "System.AreaPath": "$ProjectName$",
        "System.TeamProject": "$ProjectName$",
        "System.IterationPath": "$ProjectName$",
        "System.WorkItemType": "User Story",
        "System.State": "New",
        "System.Reason": "New",
        "System.CreatedDate": "2019-06-11T21:50:17.803Z",
        "System.CreatedBy": "Brian Blanchard <brblanch@microsoft.com>",
        "System.ChangedDate": "2019-06-28T16:56:27.07Z",
        "System.ChangedBy": "Brian Blanchard <brblanch@microsoft.com>",
        "System.Title": "Assess the workload",
        "Microsoft.VSTS.Scheduling.Effort": 0.0,
        "System.Description": "<div><span><a href=\"https://review.docs.microsoft.com/en-us/azure/architecture/cloud-adoption/migrate/migration-considerations/assess/?branch=pr-en-us-47\">https://review.docs.microsoft.com/en-us/azure/architecture/cloud-adoption/migrate/migration-considerations/assess/?branch=pr-en-us-47</a><br></span></div>",
        "System.AssignedTo": null,
        "Microsoft.VSTS.Scheduling.RemainingWork": 0.0,
        "Microsoft.VSTS.Common.Priority": 2.0,
        "System.BoardLane": null,
        "System.Tags": "Workload Template",
        "Microsoft.VSTS.TCM.Steps": null,
        "Microsoft.VSTS.TCM.Parameters": null,
        "Microsoft.VSTS.TCM.LocalDataSource": null,
        "Microsoft.VSTS.TCM.AutomationStatus": null,
        "System.History": null
      },
      "relations": [
        {
          "rel": "System.LinkTypes.Hierarchy-Forward",
          "url": "https://dev.azure.com/CAFTemplate/_apis/wit/workItems/140",
          "attributes": {
            "isLocked": "false",
            "name": "Child"
          }
        },
        {
          "rel": "System.LinkTypes.Hierarchy-Forward",
          "url": "https://dev.azure.com/CAFTemplate/_apis/wit/workItems/142",
          "attributes": {
            "isLocked": "false",
            "name": "Child"
          }
        },
        {
          "rel": "System.LinkTypes.Hierarchy-Reverse",
          "url": "https://dev.azure.com/CAFTemplate/_apis/wit/workItems/83",
          "attributes": {
            "isLocked": "false",
            "name": "Parent"
          }
        },
        {
          "rel": "System.LinkTypes.Hierarchy-Forward",
          "url": "https://dev.azure.com/CAFTemplate/_apis/wit/workItems/143",
          "attributes": {
            "isLocked": "false",
            "name": "Child"
          }
        },
        {
          "rel": "System.LinkTypes.Hierarchy-Forward",
          "url": "https://dev.azure.com/CAFTemplate/_apis/wit/workItems/139",
          "attributes": {
            "isLocked": "false",
            "name": "Child"
          }
        },
        {
          "rel": "System.LinkTypes.Hierarchy-Forward",
          "url": "https://dev.azure.com/CAFTemplate/_apis/wit/workItems/141",
          "attributes": {
            "isLocked": "false",
            "name": "Child"
          }
        }
      ],
      "url": "https://dev.azure.com/CAFTemplate/_apis/wit/workItems/134"
    },
    {
      "id": 8,
      "rev": 7,
      "fields": {
        "System.AreaPath": "$ProjectName$",
        "System.TeamProject": "$ProjectName$",
        "System.IterationPath": "$ProjectName$",
        "System.WorkItemType": "User Story",
        "System.State": "New",
        "System.Reason": "New",
        "System.CreatedDate": "2019-04-03T19:27:31.86Z",
        "System.CreatedBy": "Brian Blanchard <brblanch@microsoft.com>",
        "System.ChangedDate": "2019-06-28T16:56:27.07Z",
        "System.ChangedBy": "Brian Blanchard <brblanch@microsoft.com>",
        "System.Title": "VM - UX Server",
        "Microsoft.VSTS.Scheduling.Effort": 0.0,
        "System.Description": "VM to be migrated",
        "System.AssignedTo": null,
        "Microsoft.VSTS.Scheduling.RemainingWork": 0.0,
        "Microsoft.VSTS.Common.Priority": 2.0,
        "System.BoardLane": null,
        "System.Tags": "Workload Template",
        "Microsoft.VSTS.TCM.Steps": null,
        "Microsoft.VSTS.TCM.Parameters": null,
        "Microsoft.VSTS.TCM.LocalDataSource": null,
        "Microsoft.VSTS.TCM.AutomationStatus": null,
        "System.History": null
      },
      "relations": [
        {
          "rel": "System.LinkTypes.Hierarchy-Reverse",
          "url": "https://dev.azure.com/CAFTemplate/_apis/wit/workItems/83",
          "attributes": {
            "isLocked": "false",
            "name": "Parent"
          }
        },
        {
          "rel": "System.LinkTypes.Hierarchy-Forward",
          "url": "https://dev.azure.com/CAFTemplate/_apis/wit/workItems/9",
          "attributes": {
            "isLocked": "false",
            "name": "Child"
          }
        },
        {
          "rel": "System.LinkTypes.Hierarchy-Forward",
          "url": "https://dev.azure.com/CAFTemplate/_apis/wit/workItems/13",
          "attributes": {
            "isLocked": "false",
            "name": "Child"
          }
        },
        {
          "rel": "System.LinkTypes.Hierarchy-Forward",
          "url": "https://dev.azure.com/CAFTemplate/_apis/wit/workItems/12",
          "attributes": {
            "isLocked": "false",
            "name": "Child"
          }
        },
        {
          "rel": "System.LinkTypes.Hierarchy-Forward",
          "url": "https://dev.azure.com/CAFTemplate/_apis/wit/workItems/15",
          "attributes": {
            "isLocked": "false",
            "name": "Child"
          }
        },
        {
          "rel": "System.LinkTypes.Hierarchy-Forward",
          "url": "https://dev.azure.com/CAFTemplate/_apis/wit/workItems/14",
          "attributes": {
            "isLocked": "false",
            "name": "Child"
          }
        }
      ],
      "url": "https://dev.azure.com/CAFTemplate/_apis/wit/workItems/8"
    },
    {
      "id": 16,
      "rev": 6,
      "fields": {
        "System.AreaPath": "$ProjectName$",
        "System.TeamProject": "$ProjectName$",
        "System.IterationPath": "$ProjectName$",
        "System.WorkItemType": "User Story",
        "System.State": "New",
        "System.Reason": "New",
        "System.CreatedDate": "2019-04-03T19:27:31.86Z",
        "System.CreatedBy": "Brian Blanchard <brblanch@microsoft.com>",
        "System.ChangedDate": "2019-06-28T16:56:27.07Z",
        "System.ChangedBy": "Brian Blanchard <brblanch@microsoft.com>",
        "System.Title": "VM - Middle Tier",
        "Microsoft.VSTS.Scheduling.Effort": 0.0,
        "System.Description": "VM to be migrated",
        "System.AssignedTo": null,
        "Microsoft.VSTS.Scheduling.RemainingWork": 0.0,
        "Microsoft.VSTS.Common.Priority": 2.0,
        "System.BoardLane": null,
        "System.Tags": "Workload Template",
        "Microsoft.VSTS.TCM.Steps": null,
        "Microsoft.VSTS.TCM.Parameters": null,
        "Microsoft.VSTS.TCM.LocalDataSource": null,
        "Microsoft.VSTS.TCM.AutomationStatus": null,
        "System.History": null
      },
      "relations": [
        {
          "rel": "System.LinkTypes.Hierarchy-Reverse",
          "url": "https://dev.azure.com/CAFTemplate/_apis/wit/workItems/83",
          "attributes": {
            "isLocked": "false",
            "name": "Parent"
          }
        },
        {
          "rel": "System.LinkTypes.Hierarchy-Forward",
          "url": "https://dev.azure.com/CAFTemplate/_apis/wit/workItems/159",
          "attributes": {
            "isLocked": "false",
            "name": "Child"
          }
        },
        {
          "rel": "System.LinkTypes.Hierarchy-Forward",
          "url": "https://dev.azure.com/CAFTemplate/_apis/wit/workItems/157",
          "attributes": {
            "isLocked": "false",
            "name": "Child"
          }
        },
        {
          "rel": "System.LinkTypes.Hierarchy-Forward",
          "url": "https://dev.azure.com/CAFTemplate/_apis/wit/workItems/158",
          "attributes": {
            "isLocked": "false",
            "name": "Child"
          }
        },
        {
          "rel": "System.LinkTypes.Hierarchy-Forward",
          "url": "https://dev.azure.com/CAFTemplate/_apis/wit/workItems/156",
          "attributes": {
            "isLocked": "false",
            "name": "Child"
          }
        },
        {
          "rel": "System.LinkTypes.Hierarchy-Forward",
          "url": "https://dev.azure.com/CAFTemplate/_apis/wit/workItems/155",
          "attributes": {
            "isLocked": "false",
            "name": "Child"
          }
        }
      ],
      "url": "https://dev.azure.com/CAFTemplate/_apis/wit/workItems/16"
    },
    {
      "id": 24,
      "rev": 6,
      "fields": {
        "System.AreaPath": "$ProjectName$",
        "System.TeamProject": "$ProjectName$",
        "System.IterationPath": "$ProjectName$",
        "System.WorkItemType": "User Story",
        "System.State": "New",
        "System.Reason": "New",
        "System.CreatedDate": "2019-04-03T19:27:31.86Z",
        "System.CreatedBy": "Brian Blanchard <brblanch@microsoft.com>",
        "System.ChangedDate": "2019-06-28T16:56:27.07Z",
        "System.ChangedBy": "Brian Blanchard <brblanch@microsoft.com>",
        "System.Title": "VM 3 - SQL Server",
        "Microsoft.VSTS.Scheduling.Effort": 0.0,
        "System.Description": "VM to be migrated",
        "System.AssignedTo": null,
        "Microsoft.VSTS.Scheduling.RemainingWork": 0.0,
        "Microsoft.VSTS.Common.Priority": 2.0,
        "System.BoardLane": null,
        "System.Tags": "Workload Template",
        "Microsoft.VSTS.TCM.Steps": null,
        "Microsoft.VSTS.TCM.Parameters": null,
        "Microsoft.VSTS.TCM.LocalDataSource": null,
        "Microsoft.VSTS.TCM.AutomationStatus": null,
        "System.History": null
      },
      "relations": [
        {
          "rel": "System.LinkTypes.Hierarchy-Reverse",
          "url": "https://dev.azure.com/CAFTemplate/_apis/wit/workItems/83",
          "attributes": {
            "isLocked": "false",
            "name": "Parent"
          }
        },
        {
          "rel": "System.LinkTypes.Hierarchy-Forward",
          "url": "https://dev.azure.com/CAFTemplate/_apis/wit/workItems/153",
          "attributes": {
            "isLocked": "false",
            "name": "Child"
          }
        },
        {
          "rel": "System.LinkTypes.Hierarchy-Forward",
          "url": "https://dev.azure.com/CAFTemplate/_apis/wit/workItems/154",
          "attributes": {
            "isLocked": "false",
            "name": "Child"
          }
        },
        {
          "rel": "System.LinkTypes.Hierarchy-Forward",
          "url": "https://dev.azure.com/CAFTemplate/_apis/wit/workItems/151",
          "attributes": {
            "isLocked": "false",
            "name": "Child"
          }
        },
        {
          "rel": "System.LinkTypes.Hierarchy-Forward",
          "url": "https://dev.azure.com/CAFTemplate/_apis/wit/workItems/152",
          "attributes": {
            "isLocked": "false",
            "name": "Child"
          }
        },
        {
          "rel": "System.LinkTypes.Hierarchy-Forward",
          "url": "https://dev.azure.com/CAFTemplate/_apis/wit/workItems/150",
          "attributes": {
            "isLocked": "false",
            "name": "Child"
          }
        }
      ],
      "url": "https://dev.azure.com/CAFTemplate/_apis/wit/workItems/24"
    },
    {
      "id": 32,
      "rev": 6,
      "fields": {
        "System.AreaPath": "$ProjectName$",
        "System.TeamProject": "$ProjectName$",
        "System.IterationPath": "$ProjectName$",
        "System.WorkItemType": "User Story",
        "System.State": "New",
        "System.Reason": "New",
        "System.CreatedDate": "2019-04-03T19:27:31.86Z",
        "System.CreatedBy": "Brian Blanchard <brblanch@microsoft.com>",
        "System.ChangedDate": "2019-06-28T16:56:27.07Z",
        "System.ChangedBy": "Brian Blanchard <brblanch@microsoft.com>",
        "System.Title": "Test Workload",
        "Microsoft.VSTS.Scheduling.Effort": 0.0,
        "System.Description": "Validate funcationality of the workload",
        "System.AssignedTo": null,
        "Microsoft.VSTS.Scheduling.RemainingWork": 0.0,
        "Microsoft.VSTS.Common.Priority": 2.0,
        "System.BoardLane": null,
        "System.Tags": "Workload Template",
        "Microsoft.VSTS.TCM.Steps": null,
        "Microsoft.VSTS.TCM.Parameters": null,
        "Microsoft.VSTS.TCM.LocalDataSource": null,
        "Microsoft.VSTS.TCM.AutomationStatus": null,
        "System.History": null
      },
      "relations": [
        {
          "rel": "System.LinkTypes.Hierarchy-Forward",
          "url": "https://dev.azure.com/CAFTemplate/_apis/wit/workItems/34",
          "attributes": {
            "isLocked": "false",
            "name": "Child"
          }
        },
        {
          "rel": "System.LinkTypes.Hierarchy-Forward",
          "url": "https://dev.azure.com/CAFTemplate/_apis/wit/workItems/35",
          "attributes": {
            "isLocked": "false",
            "name": "Child"
          }
        },
        {
          "rel": "System.LinkTypes.Hierarchy-Forward",
          "url": "https://dev.azure.com/CAFTemplate/_apis/wit/workItems/36",
          "attributes": {
            "isLocked": "false",
            "name": "Child"
          }
        },
        {
          "rel": "System.LinkTypes.Hierarchy-Forward",
          "url": "https://dev.azure.com/CAFTemplate/_apis/wit/workItems/33",
          "attributes": {
            "isLocked": "false",
            "name": "Child"
          }
        },
        {
          "rel": "System.LinkTypes.Hierarchy-Reverse",
          "url": "https://dev.azure.com/CAFTemplate/_apis/wit/workItems/83",
          "attributes": {
            "isLocked": "false",
            "name": "Parent"
          }
        }
      ],
      "url": "https://dev.azure.com/CAFTemplate/_apis/wit/workItems/32"
    },
    {
      "id": 37,
      "rev": 6,
      "fields": {
        "System.AreaPath": "$ProjectName$",
        "System.TeamProject": "$ProjectName$",
        "System.IterationPath": "$ProjectName$",
        "System.WorkItemType": "User Story",
        "System.State": "New",
        "System.Reason": "New",
        "System.CreatedDate": "2019-04-03T19:27:31.86Z",
        "System.CreatedBy": "Brian Blanchard <brblanch@microsoft.com>",
        "System.ChangedDate": "2019-06-28T16:56:27.07Z",
        "System.ChangedBy": "Brian Blanchard <brblanch@microsoft.com>",
        "System.Title": "Optimize Workload Assets",
        "Microsoft.VSTS.Scheduling.Effort": 0.0,
        "System.Description": "Tune the migrated assets based on observations",
        "System.AssignedTo": null,
        "Microsoft.VSTS.Scheduling.RemainingWork": 0.0,
        "Microsoft.VSTS.Common.Priority": 2.0,
        "System.BoardLane": null,
        "System.Tags": "Workload Template",
        "Microsoft.VSTS.TCM.Steps": null,
        "Microsoft.VSTS.TCM.Parameters": null,
        "Microsoft.VSTS.TCM.LocalDataSource": null,
        "Microsoft.VSTS.TCM.AutomationStatus": null,
        "System.History": null
      },
      "relations": [
        {
          "rel": "System.LinkTypes.Hierarchy-Reverse",
          "url": "https://dev.azure.com/CAFTemplate/_apis/wit/workItems/83",
          "attributes": {
            "isLocked": "false",
            "name": "Parent"
          }
        },
        {
          "rel": "System.LinkTypes.Hierarchy-Forward",
          "url": "https://dev.azure.com/CAFTemplate/_apis/wit/workItems/38",
          "attributes": {
            "isLocked": "false",
            "name": "Child"
          }
        },
        {
          "rel": "System.LinkTypes.Hierarchy-Forward",
          "url": "https://dev.azure.com/CAFTemplate/_apis/wit/workItems/39",
          "attributes": {
            "isLocked": "false",
            "name": "Child"
          }
        },
        {
          "rel": "System.LinkTypes.Hierarchy-Forward",
          "url": "https://dev.azure.com/CAFTemplate/_apis/wit/workItems/41",
          "attributes": {
            "isLocked": "false",
            "name": "Child"
          }
        },
        {
          "rel": "System.LinkTypes.Hierarchy-Forward",
          "url": "https://dev.azure.com/CAFTemplate/_apis/wit/workItems/40",
          "attributes": {
            "isLocked": "false",
            "name": "Child"
          }
        }
      ],
      "url": "https://dev.azure.com/CAFTemplate/_apis/wit/workItems/37"
    },
    {
      "id": 42,
      "rev": 6,
      "fields": {
        "System.AreaPath": "$ProjectName$",
        "System.TeamProject": "$ProjectName$",
        "System.IterationPath": "$ProjectName$",
        "System.WorkItemType": "User Story",
        "System.State": "New",
        "System.Reason": "New",
        "System.CreatedDate": "2019-04-03T19:27:31.86Z",
        "System.CreatedBy": "Brian Blanchard <brblanch@microsoft.com>",
        "System.ChangedDate": "2019-06-28T16:56:27.07Z",
        "System.ChangedBy": "Brian Blanchard <brblanch@microsoft.com>",
        "System.Title": "Promote Workload",
        "Microsoft.VSTS.Scheduling.Effort": 0.0,
        "System.Description": "Tune the migrated assets based on testing feedback",
        "System.AssignedTo": null,
        "Microsoft.VSTS.Scheduling.RemainingWork": 0.0,
        "Microsoft.VSTS.Common.Priority": 2.0,
        "System.BoardLane": null,
        "System.Tags": "Workload Template",
        "Microsoft.VSTS.TCM.Steps": null,
        "Microsoft.VSTS.TCM.Parameters": null,
        "Microsoft.VSTS.TCM.LocalDataSource": null,
        "Microsoft.VSTS.TCM.AutomationStatus": null,
        "System.History": null
      },
      "relations": [
        {
          "rel": "System.LinkTypes.Hierarchy-Forward",
          "url": "https://dev.azure.com/CAFTemplate/_apis/wit/workItems/43",
          "attributes": {
            "isLocked": "false",
            "name": "Child"
          }
        },
        {
          "rel": "System.LinkTypes.Hierarchy-Forward",
          "url": "https://dev.azure.com/CAFTemplate/_apis/wit/workItems/47",
          "attributes": {
            "isLocked": "false",
            "name": "Child"
          }
        },
        {
          "rel": "System.LinkTypes.Hierarchy-Forward",
          "url": "https://dev.azure.com/CAFTemplate/_apis/wit/workItems/46",
          "attributes": {
            "isLocked": "false",
            "name": "Child"
          }
        },
        {
          "rel": "System.LinkTypes.Hierarchy-Reverse",
          "url": "https://dev.azure.com/CAFTemplate/_apis/wit/workItems/83",
          "attributes": {
            "isLocked": "false",
            "name": "Parent"
          }
        },
        {
          "rel": "System.LinkTypes.Hierarchy-Forward",
          "url": "https://dev.azure.com/CAFTemplate/_apis/wit/workItems/45",
          "attributes": {
            "isLocked": "false",
            "name": "Child"
          }
        },
        {
          "rel": "System.LinkTypes.Hierarchy-Forward",
          "url": "https://dev.azure.com/CAFTemplate/_apis/wit/workItems/44",
          "attributes": {
            "isLocked": "false",
            "name": "Child"
          }
        }
      ],
      "url": "https://dev.azure.com/CAFTemplate/_apis/wit/workItems/42"
    },
    {
      "id": 48,
      "rev": 6,
      "fields": {
        "System.AreaPath": "$ProjectName$",
        "System.TeamProject": "$ProjectName$",
        "System.IterationPath": "$ProjectName$",
        "System.WorkItemType": "User Story",
        "System.State": "New",
        "System.Reason": "New",
        "System.CreatedDate": "2019-04-03T19:27:31.86Z",
        "System.CreatedBy": "Brian Blanchard <brblanch@microsoft.com>",
        "System.ChangedDate": "2019-06-28T16:56:27.07Z",
        "System.ChangedBy": "Brian Blanchard <brblanch@microsoft.com>",
        "System.Title": "Decomission Retired Assets",
        "Microsoft.VSTS.Scheduling.Effort": 0.0,
        "System.Description": "Realize cost savings by terminating retired assets",
        "System.AssignedTo": null,
        "Microsoft.VSTS.Scheduling.RemainingWork": 0.0,
        "Microsoft.VSTS.Common.Priority": 2.0,
        "System.BoardLane": null,
        "System.Tags": "Workload Template",
        "Microsoft.VSTS.TCM.Steps": null,
        "Microsoft.VSTS.TCM.Parameters": null,
        "Microsoft.VSTS.TCM.LocalDataSource": null,
        "Microsoft.VSTS.TCM.AutomationStatus": null,
        "System.History": null
      },
      "relations": [
        {
          "rel": "System.LinkTypes.Hierarchy-Forward",
          "url": "https://dev.azure.com/CAFTemplate/_apis/wit/workItems/51",
          "attributes": {
            "isLocked": "false",
            "name": "Child"
          }
        },
        {
          "rel": "System.LinkTypes.Hierarchy-Forward",
          "url": "https://dev.azure.com/CAFTemplate/_apis/wit/workItems/50",
          "attributes": {
            "isLocked": "false",
            "name": "Child"
          }
        },
        {
          "rel": "System.LinkTypes.Hierarchy-Forward",
          "url": "https://dev.azure.com/CAFTemplate/_apis/wit/workItems/49",
          "attributes": {
            "isLocked": "false",
            "name": "Child"
          }
        },
        {
          "rel": "System.LinkTypes.Hierarchy-Reverse",
          "url": "https://dev.azure.com/CAFTemplate/_apis/wit/workItems/83",
          "attributes": {
            "isLocked": "false",
            "name": "Parent"
          }
        }
      ],
      "url": "https://dev.azure.com/CAFTemplate/_apis/wit/workItems/48"
    },
    {
      "id": 172,
      "rev": 2,
      "fields": {
        "System.AreaPath": "$ProjectName$",
        "System.TeamProject": "$ProjectName$",
        "System.IterationPath": "$ProjectName$",
        "System.WorkItemType": "User Story",
        "System.State": "New",
        "System.Reason": "New",
        "System.CreatedDate": "2019-06-18T15:52:09.613Z",
        "System.CreatedBy": "Brian Blanchard <brblanch@microsoft.com>",
        "System.ChangedDate": "2019-06-18T15:59:31.08Z",
        "System.ChangedBy": "Brian Blanchard <brblanch@microsoft.com>",
        "System.Title": "Update migration assessment, decision tree, and tooling",
        "Microsoft.VSTS.Scheduling.Effort": 0.0,
        "System.Description": "<div><span>Evaluate the results of the migration from the first host to inform iterative processes</span></div>",
        "System.AssignedTo": null,
        "Microsoft.VSTS.Scheduling.RemainingWork": 0.0,
        "Microsoft.VSTS.Common.Priority": 2.0,
        "System.BoardLane": null,
        "System.Tags": "First Host",
        "Microsoft.VSTS.TCM.Steps": null,
        "Microsoft.VSTS.TCM.Parameters": null,
        "Microsoft.VSTS.TCM.LocalDataSource": null,
        "Microsoft.VSTS.TCM.AutomationStatus": null,
        "System.History": null
      },
      "relations": [
        {
          "rel": "System.LinkTypes.Hierarchy-Forward",
          "url": "https://dev.azure.com/CAFTemplate/_apis/wit/workItems/174",
          "attributes": {
            "isLocked": "false",
            "name": "Child"
          }
        },
        {
          "rel": "System.LinkTypes.Hierarchy-Forward",
          "url": "https://dev.azure.com/CAFTemplate/_apis/wit/workItems/173",
          "attributes": {
            "isLocked": "false",
            "name": "Child"
          }
        },
        {
          "rel": "System.LinkTypes.Hierarchy-Reverse",
          "url": "https://dev.azure.com/CAFTemplate/_apis/wit/workItems/161",
          "attributes": {
            "isLocked": "false",
            "name": "Parent"
          }
        }
      ],
      "url": "https://dev.azure.com/CAFTemplate/_apis/wit/workItems/172"
    },
    {
      "id": 166,
      "rev": 2,
      "fields": {
        "System.AreaPath": "$ProjectName$",
        "System.TeamProject": "$ProjectName$",
        "System.IterationPath": "$ProjectName$",
        "System.WorkItemType": "User Story",
        "System.State": "New",
        "System.Reason": "New",
        "System.CreatedDate": "2019-06-18T15:48:03.6Z",
        "System.CreatedBy": "Brian Blanchard <brblanch@microsoft.com>",
        "System.ChangedDate": "2019-06-18T15:59:31.08Z",
        "System.ChangedBy": "Brian Blanchard <brblanch@microsoft.com>",
        "System.Title": "Migrate VMs",
        "Microsoft.VSTS.Scheduling.Effort": 0.0,
        "System.Description": "<div><span>Migrate a select group of VMs from the on-premises host to a host on Azure</span></div>",
        "System.AssignedTo": null,
        "Microsoft.VSTS.Scheduling.RemainingWork": 0.0,
        "Microsoft.VSTS.Common.Priority": 2.0,
        "System.BoardLane": null,
        "System.Tags": "First Host",
        "Microsoft.VSTS.TCM.Steps": null,
        "Microsoft.VSTS.TCM.Parameters": null,
        "Microsoft.VSTS.TCM.LocalDataSource": null,
        "Microsoft.VSTS.TCM.AutomationStatus": null,
        "System.History": null
      },
      "relations": [
        {
          "rel": "System.LinkTypes.Hierarchy-Forward",
          "url": "https://dev.azure.com/CAFTemplate/_apis/wit/workItems/168",
          "attributes": {
            "isLocked": "false",
            "name": "Child"
          }
        },
        {
          "rel": "System.LinkTypes.Hierarchy-Forward",
          "url": "https://dev.azure.com/CAFTemplate/_apis/wit/workItems/170",
          "attributes": {
            "isLocked": "false",
            "name": "Child"
          }
        },
        {
          "rel": "System.LinkTypes.Hierarchy-Reverse",
          "url": "https://dev.azure.com/CAFTemplate/_apis/wit/workItems/161",
          "attributes": {
            "isLocked": "false",
            "name": "Parent"
          }
        },
        {
          "rel": "System.LinkTypes.Hierarchy-Forward",
          "url": "https://dev.azure.com/CAFTemplate/_apis/wit/workItems/169",
          "attributes": {
            "isLocked": "false",
            "name": "Child"
          }
        },
        {
          "rel": "System.LinkTypes.Hierarchy-Forward",
          "url": "https://dev.azure.com/CAFTemplate/_apis/wit/workItems/167",
          "attributes": {
            "isLocked": "false",
            "name": "Child"
          }
        },
        {
          "rel": "System.LinkTypes.Hierarchy-Forward",
          "url": "https://dev.azure.com/CAFTemplate/_apis/wit/workItems/171",
          "attributes": {
            "isLocked": "false",
            "name": "Child"
          }
        }
      ],
      "url": "https://dev.azure.com/CAFTemplate/_apis/wit/workItems/166"
    },
    {
      "id": 162,
      "rev": 2,
      "fields": {
        "System.AreaPath": "$ProjectName$",
        "System.TeamProject": "$ProjectName$",
        "System.IterationPath": "$ProjectName$",
        "System.WorkItemType": "User Story",
        "System.State": "New",
        "System.Reason": "New",
        "System.CreatedDate": "2019-06-18T15:44:38.133Z",
        "System.CreatedBy": "Brian Blanchard <brblanch@microsoft.com>",
        "System.ChangedDate": "2019-06-18T15:59:31.08Z",
        "System.ChangedBy": "Brian Blanchard <brblanch@microsoft.com>",
        "System.Title": "Extend the landing zone for VMWare",
        "Microsoft.VSTS.Scheduling.Effort": 0.0,
        "System.Description": "<div><span>Resolve defined prerequisites necessary to migrate VMWare assets to Azure</span></div>",
        "System.AssignedTo": null,
        "Microsoft.VSTS.Scheduling.RemainingWork": 0.0,
        "Microsoft.VSTS.Common.Priority": 2.0,
        "System.BoardLane": null,
        "System.Tags": "First Host",
        "Microsoft.VSTS.TCM.Steps": null,
        "Microsoft.VSTS.TCM.Parameters": null,
        "Microsoft.VSTS.TCM.LocalDataSource": null,
        "Microsoft.VSTS.TCM.AutomationStatus": null,
        "System.History": null
      },
      "relations": [
        {
          "rel": "System.LinkTypes.Hierarchy-Forward",
          "url": "https://dev.azure.com/CAFTemplate/_apis/wit/workItems/164",
          "attributes": {
            "isLocked": "false",
            "name": "Child"
          }
        },
        {
          "rel": "System.LinkTypes.Hierarchy-Reverse",
          "url": "https://dev.azure.com/CAFTemplate/_apis/wit/workItems/161",
          "attributes": {
            "isLocked": "false",
            "name": "Parent"
          }
        },
        {
          "rel": "System.LinkTypes.Hierarchy-Forward",
          "url": "https://dev.azure.com/CAFTemplate/_apis/wit/workItems/165",
          "attributes": {
            "isLocked": "false",
            "name": "Child"
          }
        },
        {
          "rel": "System.LinkTypes.Hierarchy-Forward",
          "url": "https://dev.azure.com/CAFTemplate/_apis/wit/workItems/163",
          "attributes": {
            "isLocked": "false",
            "name": "Child"
          }
        }
      ],
      "url": "https://dev.azure.com/CAFTemplate/_apis/wit/workItems/162"
    },
    {
      "id": 133,
      "rev": 4,
      "fields": {
        "System.AreaPath": "$ProjectName$",
        "System.TeamProject": "$ProjectName$",
        "System.IterationPath": "$ProjectName$",
        "System.WorkItemType": "User Story",
        "System.State": "New",
        "System.Reason": "New",
        "System.CreatedDate": "2019-06-11T21:48:17.413Z",
        "System.CreatedBy": "Brian Blanchard <brblanch@microsoft.com>",
        "System.ChangedDate": "2019-06-27T18:10:38.58Z",
        "System.ChangedBy": "Brian Blanchard <brblanch@microsoft.com>",
        "System.Title": "Deploy the modified blueprint",
        "Microsoft.VSTS.Scheduling.Effort": 0.0,
        "System.Description": "<div><span><span style=\"display:inline !important;background-color:rgb(255, 255, 255);color:rgb(0, 0, 0);font-family:Segoe UI,SegoeUI,Segoe WP,Helvetica Neue,Helvetica,Tahoma,Arial,sans-serif;font-size:16px;list-style-type:decimal;\">Update the landing zone blueprint based on the impacted considerations and deploy the modified blueprint.</span><br></span></div>",
        "System.AssignedTo": null,
        "Microsoft.VSTS.Scheduling.RemainingWork": 0.0,
        "Microsoft.VSTS.Common.Priority": 2.0,
        "System.BoardLane": null,
        "System.Tags": "Ready",
        "Microsoft.VSTS.TCM.Steps": null,
        "Microsoft.VSTS.TCM.Parameters": null,
        "Microsoft.VSTS.TCM.LocalDataSource": null,
        "Microsoft.VSTS.TCM.AutomationStatus": null,
        "System.History": null
      },
      "relations": [
        {
          "rel": "System.LinkTypes.Hierarchy-Reverse",
          "url": "https://dev.azure.com/CAFTemplate/_apis/wit/workItems/121",
          "attributes": {
            "isLocked": "false",
            "name": "Parent"
          }
        }
      ],
      "url": "https://dev.azure.com/CAFTemplate/_apis/wit/workItems/133"
    },
    {
      "id": 132,
      "rev": 4,
      "fields": {
        "System.AreaPath": "$ProjectName$",
        "System.TeamProject": "$ProjectName$",
        "System.IterationPath": "$ProjectName$",
        "System.WorkItemType": "User Story",
        "System.State": "New",
        "System.Reason": "New",
        "System.CreatedDate": "2019-06-11T21:47:50.51Z",
        "System.CreatedBy": "Brian Blanchard <brblanch@microsoft.com>",
        "System.ChangedDate": "2019-06-27T18:10:38.58Z",
        "System.ChangedBy": "Brian Blanchard <brblanch@microsoft.com>",
        "System.Title": "Landing zone considerations",
        "Microsoft.VSTS.Scheduling.Effort": 0.0,
        "System.Description": "<div><span><span style=\"display:inline !important;background-color:rgb(255, 255, 255);color:rgb(0, 0, 0);font-family:Segoe UI,SegoeUI,Segoe WP,Helvetica Neue,Helvetica,Tahoma,Arial,sans-serif;font-size:16px;list-style-type:decimal;\">Review </span><a style=\"cursor:pointer;font-family:Segoe UI,SegoeUI,Segoe WP,Helvetica Neue,Helvetica,Tahoma,Arial,sans-serif;font-size:16px;outline-color:invert;\" href=\"https://review.docs.microsoft.com/en-us/azure/architecture/cloud-adoption/ready/considerations/index\">landing zone considerations</a><span style=\"display:inline !important;background-color:rgb(255, 255, 255);color:rgb(0, 0, 0);font-family:Segoe UI,SegoeUI,Segoe WP,Helvetica Neue,Helvetica,Tahoma,Arial,sans-serif;font-size:16px;list-style-type:decimal;\"> to understand the alternative decisions which could impact your landing zone design.</span><br></span></div>",
        "System.AssignedTo": null,
        "Microsoft.VSTS.Scheduling.RemainingWork": 0.0,
        "Microsoft.VSTS.Common.Priority": 2.0,
        "System.BoardLane": null,
        "System.Tags": "Ready",
        "Microsoft.VSTS.TCM.Steps": null,
        "Microsoft.VSTS.TCM.Parameters": null,
        "Microsoft.VSTS.TCM.LocalDataSource": null,
        "Microsoft.VSTS.TCM.AutomationStatus": null,
        "System.History": null
      },
      "relations": [
        {
          "rel": "System.LinkTypes.Hierarchy-Reverse",
          "url": "https://dev.azure.com/CAFTemplate/_apis/wit/workItems/121",
          "attributes": {
            "isLocked": "false",
            "name": "Parent"
          }
        }
      ],
      "url": "https://dev.azure.com/CAFTemplate/_apis/wit/workItems/132"
    },
    {
      "id": 131,
      "rev": 4,
      "fields": {
        "System.AreaPath": "$ProjectName$",
        "System.TeamProject": "$ProjectName$",
        "System.IterationPath": "$ProjectName$",
        "System.WorkItemType": "User Story",
        "System.State": "New",
        "System.Reason": "New",
        "System.CreatedDate": "2019-06-11T21:47:16.827Z",
        "System.CreatedBy": "Brian Blanchard <brblanch@microsoft.com>",
        "System.ChangedDate": "2019-06-27T18:10:38.58Z",
        "System.ChangedBy": "Brian Blanchard <brblanch@microsoft.com>",
        "System.Title": "CAF Migrate Landing Zone blueprint",
        "Microsoft.VSTS.Scheduling.Effort": 0.0,
        "System.Description": "<div><span><span style=\"display:inline !important;background-color:rgb(255, 255, 255);color:rgb(0, 0, 0);font-family:Segoe UI,SegoeUI,Segoe WP,Helvetica Neue,Helvetica,Tahoma,Arial,sans-serif;font-size:16px;list-style-type:decimal;\">Evaluate the </span><a style=\"cursor:pointer;font-family:Segoe UI,SegoeUI,Segoe WP,Helvetica Neue,Helvetica,Tahoma,Arial,sans-serif;font-size:16px;outline-color:invert;\" href=\"https://review.docs.microsoft.com/en-us/azure/architecture/cloud-adoption/ready/azure-readiness-guide/migration-landing-zone\">CAF Migrate Landing Zone blueprint</a><span style=\"display:inline !important;background-color:rgb(255, 255, 255);color:rgb(0, 0, 0);font-family:Segoe UI,SegoeUI,Segoe WP,Helvetica Neue,Helvetica,Tahoma,Arial,sans-serif;font-size:16px;list-style-type:decimal;\">. If the assumptions and decisions in that article align to your business and technical objectives, the blueprint can be used to create your landing zone.</span><br></span></div>",
        "System.AssignedTo": null,
        "Microsoft.VSTS.Scheduling.RemainingWork": 0.0,
        "Microsoft.VSTS.Common.Priority": 2.0,
        "System.BoardLane": null,
        "System.Tags": "Ready",
        "Microsoft.VSTS.TCM.Steps": null,
        "Microsoft.VSTS.TCM.Parameters": null,
        "Microsoft.VSTS.TCM.LocalDataSource": null,
        "Microsoft.VSTS.TCM.AutomationStatus": null,
        "System.History": null
      },
      "relations": [
        {
          "rel": "System.LinkTypes.Hierarchy-Reverse",
          "url": "https://dev.azure.com/CAFTemplate/_apis/wit/workItems/121",
          "attributes": {
            "isLocked": "false",
            "name": "Parent"
          }
        }
      ],
      "url": "https://dev.azure.com/CAFTemplate/_apis/wit/workItems/131"
    },
    {
      "id": 130,
      "rev": 4,
      "fields": {
        "System.AreaPath": "$ProjectName$",
        "System.TeamProject": "$ProjectName$",
        "System.IterationPath": "$ProjectName$",
        "System.WorkItemType": "User Story",
        "System.State": "New",
        "System.Reason": "New",
        "System.CreatedDate": "2019-06-11T21:46:48.79Z",
        "System.CreatedBy": "Brian Blanchard <brblanch@microsoft.com>",
        "System.ChangedDate": "2019-06-27T18:10:38.58Z",
        "System.ChangedBy": "Brian Blanchard <brblanch@microsoft.com>",
        "System.Title": "Azure Readiness Guide",
        "Microsoft.VSTS.Scheduling.Effort": 0.0,
        "System.Description": "<div><span><span style=\"display:inline !important;background-color:rgb(255, 255, 255);color:rgb(0, 0, 0);font-family:Segoe UI,SegoeUI,Segoe WP,Helvetica Neue,Helvetica,Tahoma,Arial,sans-serif;font-size:16px;list-style-type:decimal;\">Review the </span><a style=\"cursor:pointer;font-family:Segoe UI,SegoeUI,Segoe WP,Helvetica Neue,Helvetica,Tahoma,Arial,sans-serif;font-size:16px;outline-color:invert;\" href=\"https://review.docs.microsoft.com/en-us/azure/architecture/cloud-adoption/ready/azure-readiness-guide/index\">Azure Readiness Guide</a><span style=\"display:inline !important;background-color:rgb(255, 255, 255);color:rgb(0, 0, 0);font-family:Segoe UI,SegoeUI,Segoe WP,Helvetica Neue,Helvetica,Tahoma,Arial,sans-serif;font-size:16px;list-style-type:decimal;\"> to become familiar with the tools and approaches needed in landing zone creation.</span><br></span></div>",
        "System.AssignedTo": null,
        "Microsoft.VSTS.Scheduling.RemainingWork": 0.0,
        "Microsoft.VSTS.Common.Priority": 2.0,
        "System.BoardLane": null,
        "System.Tags": "Ready",
        "Microsoft.VSTS.TCM.Steps": null,
        "Microsoft.VSTS.TCM.Parameters": null,
        "Microsoft.VSTS.TCM.LocalDataSource": null,
        "Microsoft.VSTS.TCM.AutomationStatus": null,
        "System.History": null
      },
      "relations": [
        {
          "rel": "System.LinkTypes.Hierarchy-Reverse",
          "url": "https://dev.azure.com/CAFTemplate/_apis/wit/workItems/121",
          "attributes": {
            "isLocked": "false",
            "name": "Parent"
          }
        }
      ],
      "url": "https://dev.azure.com/CAFTemplate/_apis/wit/workItems/130"
    },
    {
      "id": 129,
      "rev": 3,
      "fields": {
        "System.AreaPath": "$ProjectName$",
        "System.TeamProject": "$ProjectName$",
        "System.IterationPath": "$ProjectName$",
        "System.WorkItemType": "User Story",
        "System.State": "New",
        "System.Reason": "New",
        "System.CreatedDate": "2019-06-11T21:34:49.68Z",
        "System.CreatedBy": "Brian Blanchard <brblanch@microsoft.com>",
        "System.ChangedDate": "2019-06-27T18:10:26.723Z",
        "System.ChangedBy": "Brian Blanchard <brblanch@microsoft.com>",
        "System.Title": "Update this Cloud Adoption Plan",
        "Microsoft.VSTS.Scheduling.Effort": 0.0,
        "System.Description": "<div><span><span style=\"display:inline !important;background-color:rgb(255, 255, 255);color:rgb(0, 0, 0);font-family:Segoe UI,SegoeUI,Segoe WP,Helvetica Neue,Helvetica,Tahoma,Arial,sans-serif;font-size:16px;list-style-type:decimal;\">Update this </span><a style=\"cursor:pointer;font-family:Segoe UI,SegoeUI,Segoe WP,Helvetica Neue,Helvetica,Tahoma,Arial,sans-serif;font-size:16px;outline-color:invert;\" href=\"https://review.docs.microsoft.com/en-us/azure/architecture/cloud-adoption/plan/plan-intro\">cloud adoption plan</a><span style=\"display:inline !important;background-color:rgb(255, 255, 255);color:rgb(0, 0, 0);font-family:Segoe UI,SegoeUI,Segoe WP,Helvetica Neue,Helvetica,Tahoma,Arial,sans-serif;font-size:16px;list-style-type:decimal;\"> to manage effort and change.</span><br></span></div>",
        "System.AssignedTo": null,
        "Microsoft.VSTS.Scheduling.RemainingWork": 0.0,
        "Microsoft.VSTS.Common.Priority": 2.0,
        "System.BoardLane": null,
        "System.Tags": "Plan",
        "Microsoft.VSTS.TCM.Steps": null,
        "Microsoft.VSTS.TCM.Parameters": null,
        "Microsoft.VSTS.TCM.LocalDataSource": null,
        "Microsoft.VSTS.TCM.AutomationStatus": null,
        "System.History": null
      },
      "relations": [
        {
          "rel": "System.LinkTypes.Hierarchy-Forward",
          "url": "https://dev.azure.com/CAFTemplate/_apis/wit/workItems/137",
          "attributes": {
            "isLocked": "false",
            "name": "Child"
          }
        },
        {
          "rel": "System.LinkTypes.Hierarchy-Forward",
          "url": "https://dev.azure.com/CAFTemplate/_apis/wit/workItems/135",
          "attributes": {
            "isLocked": "false",
            "name": "Child"
          }
        },
        {
          "rel": "System.LinkTypes.Hierarchy-Forward",
          "url": "https://dev.azure.com/CAFTemplate/_apis/wit/workItems/136",
          "attributes": {
            "isLocked": "false",
            "name": "Child"
          }
        },
        {
          "rel": "System.LinkTypes.Hierarchy-Reverse",
          "url": "https://dev.azure.com/CAFTemplate/_apis/wit/workItems/120",
          "attributes": {
            "isLocked": "false",
            "name": "Parent"
          }
        },
        {
          "rel": "System.LinkTypes.Hierarchy-Forward",
          "url": "https://dev.azure.com/CAFTemplate/_apis/wit/workItems/138",
          "attributes": {
            "isLocked": "false",
            "name": "Child"
          }
        }
      ],
      "url": "https://dev.azure.com/CAFTemplate/_apis/wit/workItems/129"
    },
    {
      "id": 128,
      "rev": 3,
      "fields": {
        "System.AreaPath": "$ProjectName$",
        "System.TeamProject": "$ProjectName$",
        "System.IterationPath": "$ProjectName$",
        "System.WorkItemType": "User Story",
        "System.State": "New",
        "System.Reason": "New",
        "System.CreatedDate": "2019-06-11T21:34:13.203Z",
        "System.CreatedBy": "Brian Blanchard <brblanch@microsoft.com>",
        "System.ChangedDate": "2019-06-27T18:10:26.723Z",
        "System.ChangedBy": "Brian Blanchard <brblanch@microsoft.com>",
        "System.Title": "Skills readiness plan",
        "Microsoft.VSTS.Scheduling.Effort": 0.0,
        "System.Description": "<div><span><span style=\"display:inline !important;background-color:rgb(255, 255, 255);color:rgb(0, 0, 0);font-family:Segoe UI,SegoeUI,Segoe WP,Helvetica Neue,Helvetica,Tahoma,Arial,sans-serif;font-size:16px;list-style-type:decimal;\">Create a plan for addressing </span><a style=\"cursor:pointer;font-family:Segoe UI,SegoeUI,Segoe WP,Helvetica Neue,Helvetica,Tahoma,Arial,sans-serif;font-size:16px;outline-color:invert;\" href=\"https://review.docs.microsoft.com/en-us/azure/architecture/cloud-adoption/plan/translate-roles-skills-processes\">skills readiness gaps</a><span style=\"display:inline !important;background-color:rgb(255, 255, 255);color:rgb(0, 0, 0);font-family:Segoe UI,SegoeUI,Segoe WP,Helvetica Neue,Helvetica,Tahoma,Arial,sans-serif;font-size:16px;list-style-type:decimal;\">.</span><br></span></div>",
        "System.AssignedTo": null,
        "Microsoft.VSTS.Scheduling.RemainingWork": 0.0,
        "Microsoft.VSTS.Common.Priority": 2.0,
        "System.BoardLane": null,
        "System.Tags": "Plan",
        "Microsoft.VSTS.TCM.Steps": null,
        "Microsoft.VSTS.TCM.Parameters": null,
        "Microsoft.VSTS.TCM.LocalDataSource": null,
        "Microsoft.VSTS.TCM.AutomationStatus": null,
        "System.History": null
      },
      "relations": [
        {
          "rel": "System.LinkTypes.Hierarchy-Reverse",
          "url": "https://dev.azure.com/CAFTemplate/_apis/wit/workItems/120",
          "attributes": {
            "isLocked": "false",
            "name": "Parent"
          }
        }
      ],
      "url": "https://dev.azure.com/CAFTemplate/_apis/wit/workItems/128"
    },
    {
      "id": 127,
      "rev": 4,
      "fields": {
        "System.AreaPath": "$ProjectName$",
        "System.TeamProject": "$ProjectName$",
        "System.IterationPath": "$ProjectName$",
        "System.WorkItemType": "User Story",
        "System.State": "New",
        "System.Reason": "New",
        "System.CreatedDate": "2019-06-11T21:33:50.167Z",
        "System.CreatedBy": "Brian Blanchard <brblanch@microsoft.com>",
        "System.ChangedDate": "2019-06-27T18:10:26.723Z",
        "System.ChangedBy": "Brian Blanchard <brblanch@microsoft.com>",
        "System.Title": "Initial organizational alignment",
        "Microsoft.VSTS.Scheduling.Effort": 0.0,
        "System.Description": "<div><span><span style=\"display:inline !important;background-color:rgb(255, 255, 255);color:rgb(0, 0, 0);font-family:Segoe UI,SegoeUI,Segoe WP,Helvetica Neue,Helvetica,Tahoma,Arial,sans-serif;font-size:16px;list-style-type:decimal;\">Establish a plan for </span><a style=\"cursor:pointer;font-family:Segoe UI,SegoeUI,Segoe WP,Helvetica Neue,Helvetica,Tahoma,Arial,sans-serif;font-size:16px;outline-color:invert;\" href=\"https://review.docs.microsoft.com/en-us/azure/architecture/cloud-adoption/organization/index\">organizational alignment</a><span style=\"display:inline !important;background-color:rgb(255, 255, 255);color:rgb(0, 0, 0);font-family:Segoe UI,SegoeUI,Segoe WP,Helvetica Neue,Helvetica,Tahoma,Arial,sans-serif;font-size:16px;list-style-type:decimal;\">, included defined </span><a style=\"cursor:pointer;font-family:Segoe UI,SegoeUI,Segoe WP,Helvetica Neue,Helvetica,Tahoma,Arial,sans-serif;font-size:16px;outline-color:invert;\" href=\"https://review.docs.microsoft.com/en-us/azure/architecture/cloud-adoption/organization/raci-alignment\">RACI diagrams</a><span style=\"display:inline !important;background-color:rgb(255, 255, 255);color:rgb(0, 0, 0);font-family:Segoe UI,SegoeUI,Segoe WP,Helvetica Neue,Helvetica,Tahoma,Arial,sans-serif;font-size:16px;list-style-type:decimal;\">.</span><br></span></div>",
        "System.AssignedTo": null,
        "Microsoft.VSTS.Scheduling.RemainingWork": 0.0,
        "Microsoft.VSTS.Common.Priority": 2.0,
        "System.BoardLane": null,
        "System.Tags": "Plan",
        "Microsoft.VSTS.TCM.Steps": null,
        "Microsoft.VSTS.TCM.Parameters": null,
        "Microsoft.VSTS.TCM.LocalDataSource": null,
        "Microsoft.VSTS.TCM.AutomationStatus": null,
        "System.History": null
      },
      "relations": [
        {
          "rel": "System.LinkTypes.Hierarchy-Reverse",
          "url": "https://dev.azure.com/CAFTemplate/_apis/wit/workItems/120",
          "attributes": {
            "isLocked": "false",
            "name": "Parent"
          }
        }
      ],
      "url": "https://dev.azure.com/CAFTemplate/_apis/wit/workItems/127"
    },
    {
      "id": 126,
      "rev": 3,
      "fields": {
        "System.AreaPath": "$ProjectName$",
        "System.TeamProject": "$ProjectName$",
        "System.IterationPath": "$ProjectName$",
        "System.WorkItemType": "User Story",
        "System.State": "New",
        "System.Reason": "New",
        "System.CreatedDate": "2019-06-11T21:33:30.647Z",
        "System.CreatedBy": "Brian Blanchard <brblanch@microsoft.com>",
        "System.ChangedDate": "2019-06-27T18:10:26.723Z",
        "System.ChangedBy": "Brian Blanchard <brblanch@microsoft.com>",
        "System.Title": "Digital Estate",
        "Microsoft.VSTS.Scheduling.Effort": 0.0,
        "System.Description": "<div><span><a style=\"cursor:pointer;font-family:Segoe UI,SegoeUI,Segoe WP,Helvetica Neue,Helvetica,Tahoma,Arial,sans-serif;font-size:16px;outline-color:invert;\" href=\"https://review.docs.microsoft.com/en-us/azure/architecture/cloud-adoption/digital-estate/inventory\">Inventory</a><span style=\"display:inline !important;background-color:rgb(255, 255, 255);color:rgb(0, 0, 0);font-family:Segoe UI,SegoeUI,Segoe WP,Helvetica Neue,Helvetica,Tahoma,Arial,sans-serif;font-size:16px;list-style-type:decimal;\"> and </span><a style=\"cursor:pointer;font-family:Segoe UI,SegoeUI,Segoe WP,Helvetica Neue,Helvetica,Tahoma,Arial,sans-serif;font-size:16px;outline-color:invert;\" href=\"https://review.docs.microsoft.com/en-us/azure/architecture/cloud-adoption/digital-estate/rationalize\">rationalize the digital estate</a><span style=\"display:inline !important;background-color:rgb(255, 255, 255);color:rgb(0, 0, 0);font-family:Segoe UI,SegoeUI,Segoe WP,Helvetica Neue,Helvetica,Tahoma,Arial,sans-serif;font-size:16px;list-style-type:decimal;\"> based on assumptions which align with motivations and business outcomes.</span><br></span></div>",
        "System.AssignedTo": null,
        "Microsoft.VSTS.Scheduling.RemainingWork": 0.0,
        "Microsoft.VSTS.Common.Priority": 2.0,
        "System.BoardLane": null,
        "System.Tags": "Plan",
        "Microsoft.VSTS.TCM.Steps": null,
        "Microsoft.VSTS.TCM.Parameters": null,
        "Microsoft.VSTS.TCM.LocalDataSource": null,
        "Microsoft.VSTS.TCM.AutomationStatus": null,
        "System.History": null
      },
      "relations": [
        {
          "rel": "System.LinkTypes.Hierarchy-Reverse",
          "url": "https://dev.azure.com/CAFTemplate/_apis/wit/workItems/120",
          "attributes": {
            "isLocked": "false",
            "name": "Parent"
          }
        }
      ],
      "url": "https://dev.azure.com/CAFTemplate/_apis/wit/workItems/126"
    },
    {
      "id": 125,
      "rev": 4,
      "fields": {
        "System.AreaPath": "$ProjectName$",
        "System.TeamProject": "$ProjectName$",
        "System.IterationPath": "$ProjectName$",
        "System.WorkItemType": "User Story",
        "System.State": "New",
        "System.Reason": "New",
        "System.CreatedDate": "2019-06-11T21:32:27.83Z",
        "System.CreatedBy": "Brian Blanchard <brblanch@microsoft.com>",
        "System.ChangedDate": "2019-06-27T18:10:26.723Z",
        "System.ChangedBy": "Brian Blanchard <brblanch@microsoft.com>",
        "System.Title": "First Adoption Project",
        "Microsoft.VSTS.Scheduling.Effort": 0.0,
        "System.Description": "<div><span><span style=\"display:inline !important;background-color:rgb(255, 255, 255);color:rgb(0, 0, 0);font-family:Segoe UI,SegoeUI,Segoe WP,Helvetica Neue,Helvetica,Tahoma,Arial,sans-serif;font-size:16px;list-style-type:decimal;\">In parallel to strategy and plan development, technical staff should begin implementation of a </span><a style=\"cursor:pointer;font-family:Segoe UI,SegoeUI,Segoe WP,Helvetica Neue,Helvetica,Tahoma,Arial,sans-serif;font-size:16px;outline-color:invert;\" href=\"https://review.docs.microsoft.com/en-us/azure/architecture/cloud-adoption/business-strategy/first-adoption-project\">first adoption project</a><span style=\"display:inline !important;background-color:rgb(255, 255, 255);color:rgb(0, 0, 0);font-family:Segoe UI,SegoeUI,Segoe WP,Helvetica Neue,Helvetica,Tahoma,Arial,sans-serif;font-size:16px;list-style-type:decimal;\"> to expand cloud skills.</span><br></span></div>",
        "System.AssignedTo": null,
        "Microsoft.VSTS.Scheduling.RemainingWork": 0.0,
        "Microsoft.VSTS.Common.Priority": 2.0,
        "System.BoardLane": null,
        "System.Tags": "Strategy",
        "Microsoft.VSTS.TCM.Steps": null,
        "Microsoft.VSTS.TCM.Parameters": null,
        "Microsoft.VSTS.TCM.LocalDataSource": null,
        "Microsoft.VSTS.TCM.AutomationStatus": null,
        "System.History": null
      },
      "relations": [
        {
          "rel": "System.LinkTypes.Hierarchy-Reverse",
          "url": "https://dev.azure.com/CAFTemplate/_apis/wit/workItems/119",
          "attributes": {
            "isLocked": "false",
            "name": "Parent"
          }
        }
      ],
      "url": "https://dev.azure.com/CAFTemplate/_apis/wit/workItems/125"
    },
    {
      "id": 124,
      "rev": 4,
      "fields": {
        "System.AreaPath": "$ProjectName$",
        "System.TeamProject": "$ProjectName$",
        "System.IterationPath": "$ProjectName$",
        "System.WorkItemType": "User Story",
        "System.State": "New",
        "System.Reason": "New",
        "System.CreatedDate": "2019-06-11T21:31:56.523Z",
        "System.CreatedBy": "Brian Blanchard <brblanch@microsoft.com>",
        "System.ChangedDate": "2019-06-27T18:10:26.723Z",
        "System.ChangedBy": "Brian Blanchard <brblanch@microsoft.com>",
        "System.Title": "Business Case",
        "Microsoft.VSTS.Scheduling.Effort": 0.0,
        "System.Description": "<div><span><span style=\"display:inline !important;background-color:rgb(255, 255, 255);color:rgb(0, 0, 0);font-family:Segoe UI,SegoeUI,Segoe WP,Helvetica Neue,Helvetica,Tahoma,Arial,sans-serif;font-size:16px;list-style-type:decimal;\">Develop a </span><a style=\"cursor:pointer;font-family:Segoe UI,SegoeUI,Segoe WP,Helvetica Neue,Helvetica,Tahoma,Arial,sans-serif;font-size:16px;outline-color:invert;\" href=\"https://review.docs.microsoft.com/en-us/azure/architecture/cloud-adoption/business-strategy/cloud-migration-business-case\">business case</a><span style=\"display:inline !important;background-color:rgb(255, 255, 255);color:rgb(0, 0, 0);font-family:Segoe UI,SegoeUI,Segoe WP,Helvetica Neue,Helvetica,Tahoma,Arial,sans-serif;font-size:16px;list-style-type:decimal;\"> to validate the financial model supporting the motivations and outcomes.</span><br></span></div>",
        "System.AssignedTo": null,
        "Microsoft.VSTS.Scheduling.RemainingWork": 0.0,
        "Microsoft.VSTS.Common.Priority": 2.0,
        "System.BoardLane": null,
        "System.Tags": "Strategy",
        "Microsoft.VSTS.TCM.Steps": null,
        "Microsoft.VSTS.TCM.Parameters": null,
        "Microsoft.VSTS.TCM.LocalDataSource": null,
        "Microsoft.VSTS.TCM.AutomationStatus": null,
        "System.History": null
      },
      "relations": [
        {
          "rel": "System.LinkTypes.Hierarchy-Reverse",
          "url": "https://dev.azure.com/CAFTemplate/_apis/wit/workItems/119",
          "attributes": {
            "isLocked": "false",
            "name": "Parent"
          }
        }
      ],
      "url": "https://dev.azure.com/CAFTemplate/_apis/wit/workItems/124"
    },
    {
      "id": 123,
      "rev": 4,
      "fields": {
        "System.AreaPath": "$ProjectName$",
        "System.TeamProject": "$ProjectName$",
        "System.IterationPath": "$ProjectName$",
        "System.WorkItemType": "User Story",
        "System.State": "New",
        "System.Reason": "New",
        "System.CreatedDate": "2019-06-11T21:31:37.213Z",
        "System.CreatedBy": "Brian Blanchard <brblanch@microsoft.com>",
        "System.ChangedDate": "2019-06-27T18:10:26.723Z",
        "System.ChangedBy": "Brian Blanchard <brblanch@microsoft.com>",
        "System.Title": "Business Outcomes",
        "Microsoft.VSTS.Scheduling.Effort": 0.0,
        "System.Description": "<div><span><span style=\"display:inline !important;background-color:rgb(255, 255, 255);color:rgb(0, 0, 0);font-family:Segoe UI,SegoeUI,Segoe WP,Helvetica Neue,Helvetica,Tahoma,Arial,sans-serif;font-size:16px;list-style-type:decimal;\">Engage motivated stakeholders and executives to document specific </span><a style=\"cursor:pointer;font-family:Segoe UI,SegoeUI,Segoe WP,Helvetica Neue,Helvetica,Tahoma,Arial,sans-serif;font-size:16px;outline-color:invert;\" href=\"https://review.docs.microsoft.com/en-us/azure/architecture/cloud-adoption/business-strategy/business-outcomes/index\">business outcomes</a><span style=\"display:inline !important;background-color:rgb(255, 255, 255);color:rgb(0, 0, 0);font-family:Segoe UI,SegoeUI,Segoe WP,Helvetica Neue,Helvetica,Tahoma,Arial,sans-serif;font-size:16px;list-style-type:decimal;\">.</span><br></span></div>",
        "System.AssignedTo": null,
        "Microsoft.VSTS.Scheduling.RemainingWork": 0.0,
        "Microsoft.VSTS.Common.Priority": 2.0,
        "System.BoardLane": null,
        "System.Tags": "Strategy",
        "Microsoft.VSTS.TCM.Steps": null,
        "Microsoft.VSTS.TCM.Parameters": null,
        "Microsoft.VSTS.TCM.LocalDataSource": null,
        "Microsoft.VSTS.TCM.AutomationStatus": null,
        "System.History": null
      },
      "relations": [
        {
          "rel": "System.LinkTypes.Hierarchy-Reverse",
          "url": "https://dev.azure.com/CAFTemplate/_apis/wit/workItems/119",
          "attributes": {
            "isLocked": "false",
            "name": "Parent"
          }
        }
      ],
      "url": "https://dev.azure.com/CAFTemplate/_apis/wit/workItems/123"
    },
    {
      "id": 122,
      "rev": 4,
      "fields": {
        "System.AreaPath": "$ProjectName$",
        "System.TeamProject": "$ProjectName$",
        "System.IterationPath": "$ProjectName$",
        "System.WorkItemType": "User Story",
        "System.State": "New",
        "System.Reason": "New",
        "System.CreatedDate": "2019-06-11T21:30:54.52Z",
        "System.CreatedBy": "Brian Blanchard <brblanch@microsoft.com>",
        "System.ChangedDate": "2019-06-27T18:10:26.723Z",
        "System.ChangedBy": "Brian Blanchard <brblanch@microsoft.com>",
        "System.Title": "Motivations",
        "Microsoft.VSTS.Scheduling.Effort": 0.0,
        "System.Description": "<div><span style=\"display:inline !important;background-color:rgb(255, 255, 255);font-family:Segoe UI,SegoeUI,Segoe WP,Helvetica Neue,Helvetica,Tahoma,Arial,sans-serif;\">Meet with key stakeholders and executives to d</span><span><span style=\"display:inline !important;background-color:rgb(255, 255, 255);color:rgb(0, 0, 0);font-family:Segoe UI,SegoeUI,Segoe WP,Helvetica Neue,Helvetica,Tahoma,Arial,sans-serif;font-size:16px;list-style-type:decimal;\">ocument the </span><a style=\"cursor:pointer;font-family:Segoe UI,SegoeUI,Segoe WP,Helvetica Neue,Helvetica,Tahoma,Arial,sans-serif;font-size:16px;outline-color:invert;\" href=\"https://review.docs.microsoft.com/en-us/azure/architecture/cloud-adoption/business-strategy/motivations-why-are-we-moving-to-the-cloud\">motivations</a><span style=\"display:inline !important;background-color:rgb(255, 255, 255);color:rgb(0, 0, 0);font-family:Segoe UI,SegoeUI,Segoe WP,Helvetica Neue,Helvetica,Tahoma,Arial,sans-serif;font-size:16px;list-style-type:decimal;\"> which are driving an interest in cloud adoption.</span><br></span></div>",
        "System.AssignedTo": null,
        "Microsoft.VSTS.Scheduling.RemainingWork": 0.0,
        "Microsoft.VSTS.Common.Priority": 2.0,
        "System.BoardLane": null,
        "System.Tags": "Strategy",
        "Microsoft.VSTS.TCM.Steps": null,
        "Microsoft.VSTS.TCM.Parameters": null,
        "Microsoft.VSTS.TCM.LocalDataSource": null,
        "Microsoft.VSTS.TCM.AutomationStatus": null,
        "System.History": null
      },
      "relations": [
        {
          "rel": "System.LinkTypes.Hierarchy-Reverse",
          "url": "https://dev.azure.com/CAFTemplate/_apis/wit/workItems/119",
          "attributes": {
            "isLocked": "false",
            "name": "Parent"
          }
        }
      ],
      "url": "https://dev.azure.com/CAFTemplate/_apis/wit/workItems/122"
    }
  ],
  "HttpStatusCode": 0,
  "Message": null
}