{
  "count": 5,
  "value": [
    {
      "id": 275,
      "rev": 2,
      "fields": {
        "System.AreaPath": "Website",
        "System.TeamProject": "Website",
        "System.IterationPath": "Website\\Iteration 1",
        "System.WorkItemType": "Epic",
        "System.State": "New",
        "System.Reason": "New",
        "System.CreatedDate": "2019-01-25T21:05:35.747Z",
        "System.CreatedBy": "Sachin Raj <sraj@microsoft.com>",
        "System.ChangedDate": "2019-01-25T21:05:35.967Z",
        "System.ChangedBy": "Sachin Raj <sraj@microsoft.com>",
        "System.Title": "Vendor Management",
        "Microsoft.VSTS.Scheduling.Effort": 0.0,
        "System.Description": null,
        "System.AssignedTo": null,
        "Microsoft.VSTS.Scheduling.RemainingWork": 0.0,
        "Microsoft.VSTS.Common.Priority": 2.0,
        "System.BoardLane": null,
        "System.Tags": null,
        "Microsoft.VSTS.TCM.Steps": null,
        "Microsoft.VSTS.TCM.Parameters": null,
        "Microsoft.VSTS.TCM.LocalDataSource": null,
        "Microsoft.VSTS.TCM.AutomationStatus": null,
        "System.History": null
      },
      "relations": null,
      "url": "https://dev.azure.com/tailwindtraders/_apis/wit/workItems/275"
    },
    {
      "id": 274,
      "rev": 2,
      "fields": {
        "System.AreaPath": "Website",
        "System.TeamProject": "Website",
        "System.IterationPath": "Website\\Iteration 1",
        "System.WorkItemType": "Epic",
        "System.State": "New",
        "System.Reason": "New",
        "System.CreatedDate": "2019-01-25T21:05:26.81Z",
        "System.CreatedBy": "Sachin Raj <sraj@microsoft.com>",
        "System.ChangedDate": "2019-01-25T21:05:27.077Z",
        "System.ChangedBy": "Sachin Raj <sraj@microsoft.com>",
        "System.Title": "Payments",
        "Microsoft.VSTS.Scheduling.Effort": 0.0,
        "System.Description": null,
        "System.AssignedTo": null,
        "Microsoft.VSTS.Scheduling.RemainingWork": 0.0,
        "Microsoft.VSTS.Common.Priority": 2.0,
        "System.BoardLane": null,
        "System.Tags": null,
        "Microsoft.VSTS.TCM.Steps": null,
        "Microsoft.VSTS.TCM.Parameters": null,
        "Microsoft.VSTS.TCM.LocalDataSource": null,
        "Microsoft.VSTS.TCM.AutomationStatus": null,
        "System.History": null
      },
      "relations": [
        {
          "rel": "System.LinkTypes.Hierarchy-Forward",
          "url": "https://dev.azure.com/tailwindtraders/_apis/wit/workItems/270",
          "attributes": {
            "isLocked": "false"
          }
        },
        {
          "rel": "System.LinkTypes.Hierarchy-Forward",
          "url": "https://dev.azure.com/tailwindtraders/_apis/wit/workItems/277",
          "attributes": {
            "isLocked": "false"
          }
        },
        {
          "rel": "System.LinkTypes.Hierarchy-Forward",
          "url": "https://dev.azure.com/tailwindtraders/_apis/wit/workItems/267",
          "attributes": {
            "isLocked": "false"
          }
        }
      ],
      "url": "https://dev.azure.com/tailwindtraders/_apis/wit/workItems/274"
    },
    {
      "id": 273,
      "rev": 2,
      "fields": {
        "System.AreaPath": "Website",
        "System.TeamProject": "Website",
        "System.IterationPath": "Website\\Iteration 1",
        "System.WorkItemType": "Epic",
        "System.State": "New",
        "System.Reason": "New",
        "System.CreatedDate": "2019-01-25T21:05:19.763Z",
        "System.CreatedBy": "Sachin Raj <sraj@microsoft.com>",
        "System.ChangedDate": "2019-01-25T21:05:20.137Z",
        "System.ChangedBy": "Sachin Raj <sraj@microsoft.com>",
        "System.Title": "Customer Management",
        "Microsoft.VSTS.Scheduling.Effort": 0.0,
        "System.Description": null,
        "System.AssignedTo": null,
        "Microsoft.VSTS.Scheduling.RemainingWork": 0.0,
        "Microsoft.VSTS.Common.Priority": 2.0,
        "System.BoardLane": null,
        "System.Tags": null,
        "Microsoft.VSTS.TCM.Steps": null,
        "Microsoft.VSTS.TCM.Parameters": null,
        "Microsoft.VSTS.TCM.LocalDataSource": null,
        "Microsoft.VSTS.TCM.AutomationStatus": null,
        "System.History": null
      },
      "relations": [
        {
          "rel": "System.LinkTypes.Hierarchy-Forward",
          "url": "https://dev.azure.com/tailwindtraders/_apis/wit/workItems/276",
          "attributes": {
            "isLocked": "false"
          }
        },
        {
          "rel": "System.LinkTypes.Hierarchy-Forward",
          "url": "https://dev.azure.com/tailwindtraders/_apis/wit/workItems/265",
          "attributes": {
            "isLocked": "false"
          }
        }
      ],
      "url": "https://dev.azure.com/tailwindtraders/_apis/wit/workItems/273"
    },
    {
      "id": 272,
      "rev": 3,
      "fields": {
        "System.AreaPath": "Website",
        "System.TeamProject": "Website",
        "System.IterationPath": "Website\\Iteration 2",
        "System.WorkItemType": "Epic",
        "System.State": "New",
        "System.Reason": "New",
        "System.CreatedDate": "2019-01-25T21:05:03.247Z",
        "System.CreatedBy": "Sachin Raj <sraj@microsoft.com>",
        "System.ChangedDate": "2019-01-25T22:00:19.863Z",
        "System.ChangedBy": "Sachin Raj <sraj@microsoft.com>",
        "System.Title": "Loyalty Membership",
        "Microsoft.VSTS.Scheduling.Effort": 0.0,
        "System.Description": null,
        "System.AssignedTo": null,
        "Microsoft.VSTS.Scheduling.RemainingWork": 0.0,
        "Microsoft.VSTS.Common.Priority": 2.0,
        "System.BoardLane": null,
        "System.Tags": null,
        "Microsoft.VSTS.TCM.Steps": null,
        "Microsoft.VSTS.TCM.Parameters": null,
        "Microsoft.VSTS.TCM.LocalDataSource": null,
        "Microsoft.VSTS.TCM.AutomationStatus": null,
        "System.History": null
      },
      "relations": [
        {
          "rel": "System.LinkTypes.Hierarchy-Forward",
          "url": "https://dev.azure.com/tailwindtraders/_apis/wit/workItems/269",
          "attributes": {
            "isLocked": "false"
          }
        },
        {
          "rel": "System.LinkTypes.Hierarchy-Forward",
          "url": "https://dev.azure.com/tailwindtraders/_apis/wit/workItems/268",
          "attributes": {
            "isLocked": "false"
          }
        }
      ],
      "url": "https://dev.azure.com/tailwindtraders/_apis/wit/workItems/272"
    },
    {
      "id": 271,
      "rev": 3,
      "fields": {
        "System.AreaPath": "Website",
        "System.TeamProject": "Website",
        "System.IterationPath": "Website\\Iteration 3",
        "System.WorkItemType": "Epic",
        "System.State": "New",
        "System.Reason": "New",
        "System.CreatedDate": "2019-01-25T21:04:55.327Z",
        "System.CreatedBy": "Sachin Raj <sraj@microsoft.com>",
        "System.ChangedDate": "2019-01-25T22:00:32.677Z",
        "System.ChangedBy": "Sachin Raj <sraj@microsoft.com>",
        "System.Title": "Shopping Cart",
        "Microsoft.VSTS.Scheduling.Effort": 0.0,
        "System.Description": null,
        "System.AssignedTo": null,
        "Microsoft.VSTS.Scheduling.RemainingWork": 0.0,
        "Microsoft.VSTS.Common.Priority": 2.0,
        "System.BoardLane": null,
        "System.Tags": null,
        "Microsoft.VSTS.TCM.Steps": null,
        "Microsoft.VSTS.TCM.Parameters": null,
        "Microsoft.VSTS.TCM.LocalDataSource": null,
        "Microsoft.VSTS.TCM.AutomationStatus": null,
        "System.History": null
      },
      "relations": [
        {
          "rel": "System.LinkTypes.Hierarchy-Forward",
          "url": "https://dev.azure.com/tailwindtraders/_apis/wit/workItems/266",
          "attributes": {
            "isLocked": "false"
          }
        },
        {
          "rel": "System.LinkTypes.Hierarchy-Forward",
          "url": "https://dev.azure.com/tailwindtraders/_apis/wit/workItems/263",
          "attributes": {
            "isLocked": "false"
          }
        },
        {
          "rel": "System.LinkTypes.Hierarchy-Forward",
          "url": "https://dev.azure.com/tailwindtraders/_apis/wit/workItems/264",
          "attributes": {
            "isLocked": "false"
          }
        }
      ],
      "url": "https://dev.azure.com/tailwindtraders/_apis/wit/workItems/271"
    }
  ],
  "HttpStatusCode": 0,
  "Message": null
}